librecubo/__init__.py
librecubo/main.py
librecubo/utils.py
librecubo-0.0.21.dist-info/LICENSE.md
librecubo-0.0.21.dist-info/METADATA
librecubo-0.0.21.dist-info/WHEEL
librecubo-0.0.21.dist-info/RECORD
