Metadata-Version: 2.1
Name: librecubo
Version: 0.0.21
Summary: This is a template repository for Python projects that use Poetry for their dependency management.
Home-page: https://github.com/jfloresf17/librecubo
Author: Jair Flores
Author-email: fjfloresf0517@gmail.com
Requires-Python: >=3.9,<4.0
Classifier: Programming Language :: Python :: 3
Classifier: Programming Language :: Python :: 3.9
Classifier: Programming Language :: Python :: 3.10
Classifier: Programming Language :: Python :: 3.11
Classifier: Programming Language :: Python :: 3.12
Requires-Dist: cloudpickle (==3.0.0)
Requires-Dist: cubo (==2023.7.2)
Requires-Dist: rioxarray (==0.15.0)
Requires-Dist: tqdm (==4.66.1)
Project-URL: Documentation, https://jfloresf17.github.io/librecubo/
Project-URL: Repository, https://github.com/jfloresf17/librecubo
